fludashboard/.Rhistory
fludashboard/README.md
fludashboard/__init__.py
fludashboard/__init__.pyc
fludashboard/app.py
fludashboard/runwsgi.py
fludashboard/runwsgi.sh
fludashboard/settings.py
fludashboard/__pycache__/__init__.cpython-34.pyc
fludashboard/__pycache__/__init__.cpython-35.pyc
fludashboard/__pycache__/__init__.cpython-36.pyc
fludashboard/__pycache__/app.cpython-35.pyc
fludashboard/__pycache__/app.cpython-36.pyc
fludashboard/__pycache__/calc_alert.cpython-34.pyc
fludashboard/__pycache__/calc_srag_alert.cpython-34.pyc
fludashboard/__pycache__/calc_srag_alert.cpython-35.pyc
fludashboard/__pycache__/curve_chart.cpython-34.pyc
fludashboard/__pycache__/episem.cpython-35.pyc
fludashboard/__pycache__/runwsgi.cpython-35.pyc
fludashboard/__pycache__/runwsgi.cpython-36.pyc
fludashboard/__pycache__/settings.cpython-36.pyc
fludashboard/__pycache__/srag_data.cpython-34.pyc
fludashboard/__pycache__/srag_data.cpython-35.pyc
fludashboard/__pycache__/utils.cpython-34.pyc
fludashboard/__pycache__/utils.cpython-35.pyc
fludashboard/data/.gitkeep
fludashboard/data/br-states.json
fludashboard/docs/layout.epz
fludashboard/docs/img/detalhado.png
fludashboard/docs/img/resumido.png
fludashboard/libs/__init__.py
fludashboard/libs/calc_flu_alert.py
fludashboard/libs/charts.py
fludashboard/libs/episem.py
fludashboard/libs/flu_data.py
fludashboard/libs/migration.py
fludashboard/libs/utils.py
fludashboard/libs/views.py
fludashboard/libs/views.py.orig
fludashboard/libs/__pycache__/__init__.cpython-35.pyc
fludashboard/libs/__pycache__/__init__.cpython-36.pyc
fludashboard/libs/__pycache__/calc_flu_alert.cpython-35.pyc
fludashboard/libs/__pycache__/calc_flu_alert.cpython-36.pyc
fludashboard/libs/__pycache__/charts.cpython-36.pyc
fludashboard/libs/__pycache__/episem.cpython-35.pyc
fludashboard/libs/__pycache__/episem.cpython-36.pyc
fludashboard/libs/__pycache__/flu_data.cpython-35.pyc
fludashboard/libs/__pycache__/flu_data.cpython-36.pyc
fludashboard-0.4.0.dist-info/DESCRIPTION.rst
fludashboard-0.4.0.dist-info/METADATA
fludashboard-0.4.0.dist-info/RECORD
fludashboard-0.4.0.dist-info/WHEEL
fludashboard-0.4.0.dist-info/entry_points.txt
fludashboard-0.4.0.dist-info/metadata.json
fludashboard-0.4.0.dist-info/top_level.txt
