Metadata-Version: 2.0
Name: fludashboard
Version: 0.4.0
Summary: Flu Dashboard
Home-page: https://github.com/FluVigilanciaBR/fludashboard
Author: Marcelo F C Gomes, Ivan Ogasawara
Author-email: marcelo.gomes@fiocruz.br, ivan.ogasawara@gmail.com
License: GNU General Public License v3
Keywords: fludashboard
Platform: UNKNOWN
Classifier: Development Status :: 4 - Beta
Classifier: Intended Audience :: Developers
Classifier: License :: OSI Approved :: GNU General Public License v3 (GPLv3)
Classifier: Natural Language :: English
Classifier: Programming Language :: Python :: 3
Classifier: Programming Language :: Python :: 3.5
Classifier: Programming Language :: Python :: 3.6
Requires-Dist: pandas (>=0.21)
Requires-Dist: numpy
Requires-Dist: flask
Requires-Dist: unidecode
Requires-Dist: sqlalchemy
Requires-Dist: psycopg2
Requires-Dist: pyyaml
Requires-Dist: cufflinks
Requires-Dist: plotly (==2.5.1)
Requires-Dist: ipython
